tcms_django_plugin/__init__.py
tcms_django_plugin/result.py
tcms_django_plugin/version.py
kiwitcms_django_plugin-12.7.dist-info/LICENSE
kiwitcms_django_plugin-12.7.dist-info/METADATA
kiwitcms_django_plugin-12.7.dist-info/WHEEL
kiwitcms_django_plugin-12.7.dist-info/top_level.txt
kiwitcms_django_plugin-12.7.dist-info/RECORD
