Metadata-Version: 2.1
Name: kiwitcms-django-plugin
Version: 12.7
Summary: Django test runner plugin for Kiwi TCMS
Home-page: https://github.com/kiwitcms/django-plugin
Author: Bryan Mutai
Author-email: work@bryanmutai.co
Maintainer: Kiwi TCMS
Maintainer-email: info@kiwitcms.org
License: GPLv3
Classifier: Development Status :: 3 - Alpha
Classifier: Intended Audience :: Developers
Classifier: Intended Audience :: System Administrators
Classifier: License :: OSI Approved :: GNU General Public License v3 (GPLv3)
Classifier: Operating System :: POSIX
Classifier: Programming Language :: Python
Classifier: Programming Language :: Python :: 3.7
Classifier: Programming Language :: Python :: 3.8
Classifier: Programming Language :: Python :: 3.9
Classifier: Programming Language :: Python :: 3.11
Classifier: Topic :: Software Development
Classifier: Topic :: Software Development :: Libraries :: Python Modules
Classifier: Topic :: Software Development :: Quality Assurance
Classifier: Topic :: Software Development :: Testing
Requires-Python: >=3.6
License-File: LICENSE
Requires-Dist: Django
Requires-Dist: tcms-api (>=12.7)
